pyutu/__init__.py
pyutu/cli.py
pyutu/client.py
pyutu/test_pyutu.py
pyutu-0.4.7.dist-info/DESCRIPTION.rst
pyutu-0.4.7.dist-info/METADATA
pyutu-0.4.7.dist-info/RECORD
pyutu-0.4.7.dist-info/WHEEL
pyutu-0.4.7.dist-info/entry_points.txt
pyutu-0.4.7.dist-info/metadata.json
pyutu-0.4.7.dist-info/top_level.txt
