Metadata-Version: 1.1
Name: pyutu
Version: 0.4.7
Summary: Python library for interaction with the AWS Pricing API
Home-page: https://github.com/lashex/pyutu
Author: Brett Francis
Author-email: brett_francis@me.com
License: The MIT License (MIT)
